setup.cfg
setup.py
pysunsky/__init__.py
pysunsky/api.py
pysunsky.egg-info/PKG-INFO
pysunsky.egg-info/SOURCES.txt
pysunsky.egg-info/dependency_links.txt
pysunsky.egg-info/not-zip-safe
pysunsky.egg-info/top_level.txt