Metadata-Version: 1.2
Name: pysunsky
Version: 1.0.1
Summary: Simple SDK for use the Open API's of sunsky-online.com
Home-page: https://github.com/progressify/sunsky-python-api-service
Author: Progressify
Author-email: info@progressify.dev
License: MIT
Keywords: sunsky,api,e-commerce,dropshipping
Platform: UNKNOWN
Classifier: Programming Language :: Python
Classifier: Programming Language :: Python :: 3
Classifier: Programming Language :: Python :: 3.7
Requires-Python: >=3.7
